MANIFEST.in
README.rst
requirements.txt
setup.py
apy_users/__init__.py
apy_users/adapters.py
apy_users/controllers.py
apy_users/entities.py
apy_users/model.py
apy_users.egg-info/PKG-INFO
apy_users.egg-info/SOURCES.txt
apy_users.egg-info/dependency_links.txt
apy_users.egg-info/not-zip-safe
apy_users.egg-info/requires.txt
apy_users.egg-info/top_level.txt
apy_users/config/parameters.yml
apy_users/config/routes.yml
apy_users/config/services.yml