Metadata-Version: 1.0
Name: apy-users
Version: 0.0.3
Summary: Provides user management and API authentication for your apy project
Home-page: https://github.com/stagecoachio/apy-users
Author: Felix Carmona
Author-email: mail@felixcarmona.com
License: UNKNOWN
Platform: UNKNOWN
